{"date":"2026-06-06","tz":"Europe/Amsterdam","locations":{"901":{"n":2,"occ":[0,null,0,null,null,null,null,0,null,0,null,null,0,null,0,null,0,null,null,null,null,null,null,null]},"1840":{"n":2,"occ":[0,null,0,null,null,null,null,50,null,50,null,null,50,null,50,null,50,null,null,null,null,null,null,null]},"1971":{"n":2,"occ":[0,null,0,null,null,null,null,0,null,0,null,null,0,null,0,null,0,null,null,null,null,null,null,null]},"2123":{"n":2,"occ":[50,null,50,null,null,null,null,50,null,50,null,null,0,null,0,null,50,null,null,null,null,null,null,null]},"2455":{"n":2,"occ":[50,null,50,null,null,null,null,50,null,50,null,null,50,null,0,null,0,null,null,null,null,null,null,null]},"2807":{"n":2,"occ":[0,null,0,null,null,null,null,0,null,0,null,null,50,null,50,null,0,null,null,null,null,null,null,null]},"5221":{"n":6,"occ":[17,null,17,null,null,null,null,17,null,0,null,null,0,null,17,null,0,null,null,null,null,null,null,null]},"591a1d10-d48e-11f0-90bf-42010aa400b8":{"n":6,"occ":[0,null,0,null,null,null,null,0,null,0,null,null,0,null,0,null,0,null,null,null,null,null,null,null]},"60b42f3c-bcd9-11ec-9b20-42010a84006e":{"n":2,"occ":[50,null,50,null,null,null,null,50,null,50,null,null,50,null,50,null,50,null,null,null,null,null,null,null]},"853cd02a-4f3c-11e8-a6f4-42010a840002":{"n":2,"occ":[0,null,0,null,null,null,null,0,null,0,null,null,0,null,0,null,0,null,null,null,null,null,null,null]},"b3e034e8-ce88-11eb-919c-42010a840030":{"n":2,"occ":[0,null,0,null,null,null,null,0,null,0,null,null,0,null,0,null,0,null,null,null,null,null,null,null]},"NLLOC008617":{"n":2,"occ":[50,null,100,null,null,null,null,50,null,50,null,null,0,null,50,null,50,null,null,null,null,null,null,null]},"688a8dbc-c902-11eb-88a1-42010a840009":{"n":2,"occ":[100,null,100,null,null,null,null,100,null,100,null,null,100,null,100,null,100,null,null,null,null,null,null,null]},"bf1bb4e6-1596-11f0-bb60-42010aa400b8":{"n":2,"occ":[0,null,0,null,null,null,null,0,null,0,null,null,0,null,0,null,0,null,null,null,null,null,null,null]},"b9388a78-af76-11e8-a52c-42010a840002":{"n":2,"occ":[0,null,0,null,null,null,null,0,null,0,null,null,0,null,0,null,0,null,null,null,null,null,null,null]},"d9ba75aa104c4696a72747b924885f73":{"n":10,"occ":[90,null,90,null,null,null,null,20,null,20,null,null,70,null,70,null,70,null,null,null,null,null,null,null]},"b033f5ec-4f3c-11e8-b265-42010a840002":{"n":2,"occ":[0,null,0,null,null,null,null,0,null,0,null,null,0,null,0,null,0,null,null,null,null,null,null,null]},"179dbc40-aed0-11f0-b348-42010aa400b8":{"n":2,"occ":[0,null,0,null,null,null,null,0,null,0,null,null,0,null,0,null,0,null,null,null,null,null,null,null]},"aa6aba3a-70f5-11e8-94a1-42010a840002":{"n":2,"occ":[100,null,100,null,null,null,null,100,null,100,null,null,100,null,100,null,100,null,null,null,null,null,null,null]},"0c9b4dee-1c44-11ec-b081-42010a84002c":{"n":2,"occ":[0,null,0,null,null,null,null,0,null,0,null,null,0,null,0,null,0,null,null,null,null,null,null,null]},"91d00320-d54e-11f0-b376-42010aa400b8":{"n":2,"occ":[50,null,50,null,null,null,null,50,null,50,null,null,50,null,50,null,50,null,null,null,null,null,null,null]},"982357be-9808-11f0-b160-42010aa400b8":{"n":2,"occ":[0,null,0,null,null,null,null,0,null,0,null,null,0,null,0,null,0,null,null,null,null,null,null,null]},"40320be2-ca4c-11f0-aa5a-42010aa400b8":{"n":2,"occ":[0,null,0,null,null,null,null,0,null,0,null,null,0,null,0,null,0,null,null,null,null,null,null,null]},"09c98b16-8e30-11e9-9597-42010a840003":{"n":2,"occ":[50,null,50,null,null,null,null,50,null,50,null,null,50,null,50,null,50,null,null,null,null,null,null,null]},"51d20036-96fa-11ea-afcc-42010a840003":{"n":2,"occ":[0,null,0,null,null,null,null,0,null,0,null,null,0,null,0,null,0,null,null,null,null,null,null,null]},"D2860FDF-3F99-4410-989A-4B7C9C6B269D":{"n":2,"occ":[0,null,0,null,null,null,null,0,null,0,null,null,50,null,50,null,0,null,null,null,null,null,null,null]},"3d7c55a0-98d1-45bf-a265-81b1321bd6da":{"n":2,"occ":[0,null,0,null,null,null,null,0,null,0,null,null,0,null,50,null,0,null,null,null,null,null,null,null]},"f6f95b50-9c54-11e9-b438-42010a840003":{"n":2,"occ":[0,null,0,null,null,null,null,0,null,0,null,null,0,null,0,null,0,null,null,null,null,null,null,null]},"29aac6ec-0285-11ea-b19d-42010a840003":{"n":2,"occ":[0,null,0,null,null,null,null,0,null,0,null,null,0,null,0,null,0,null,null,null,null,null,null,null]},"4129e6d4-ba3e-11ee-b408-42010aa40fc0":{"n":2,"occ":[0,null,0,null,null,null,null,0,null,0,null,null,0,null,0,null,0,null,null,null,null,null,null,null]},"9a61c2fc-005c-11f0-8ce6-42010aa400b8":{"n":2,"occ":[50,null,50,null,null,null,null,50,null,50,null,null,50,null,50,null,50,null,null,null,null,null,null,null]},"7cd5289c-78f8-11e9-b8be-42010a840003":{"n":2,"occ":[0,null,0,null,null,null,null,0,null,0,null,null,0,null,0,null,0,null,null,null,null,null,null,null]},"7cecb0f2-78f8-11e9-bde7-42010a840003":{"n":2,"occ":[0,null,0,null,null,null,null,0,null,0,null,null,0,null,0,null,0,null,null,null,null,null,null,null]},"135f4a9a-c33e-11f0-ab31-42010aa400b8":{"n":2,"occ":[50,null,50,null,null,null,null,50,null,50,null,null,50,null,50,null,50,null,null,null,null,null,null,null]},"7bfd42f0-79cb-11ee-8cfc-42010aa40fc0":{"n":2,"occ":[0,null,0,null,null,null,null,0,null,0,null,null,0,null,0,null,0,null,null,null,null,null,null,null]},"a1adfc6e-71f2-11ee-8a34-42010aa40fc0":{"n":2,"occ":[0,null,0,null,null,null,null,0,null,0,null,null,0,null,0,null,0,null,null,null,null,null,null,null]},"856d6096-4f3c-11e8-ac39-42010a840002":{"n":2,"occ":[50,null,50,null,null,null,null,50,null,50,null,null,50,null,50,null,50,null,null,null,null,null,null,null]},"06a35a5c-cc51-11ee-8549-42010aa40fc0":{"n":2,"occ":[0,null,0,null,null,null,null,0,null,0,null,null,0,null,0,null,0,null,null,null,null,null,null,null]},"a51d1e3a-2b2b-11ec-a12c-42010a840003":{"n":2,"occ":[50,null,50,null,null,null,null,50,null,50,null,null,50,null,50,null,50,null,null,null,null,null,null,null]},"7d4a82cc-3436-11eb-853f-42010a840003":{"n":2,"occ":[50,null,50,null,null,null,null,50,null,50,null,null,50,null,50,null,50,null,null,null,null,null,null,null]},"c7ec3738-6034-11eb-a4cb-42010a840003":{"n":2,"occ":[50,null,50,null,null,null,null,50,null,50,null,null,50,null,50,null,50,null,null,null,null,null,null,null]},"9fc5ca9c-9286-11f0-a777-42010aa400b8":{"n":2,"occ":[0,null,0,null,null,null,null,0,null,0,null,null,0,null,0,null,0,null,null,null,null,null,null,null]},"cf8ecfe4-6d5f-11ec-971b-42010a84002a":{"n":2,"occ":[0,null,0,null,null,null,null,0,null,0,null,null,0,null,0,null,0,null,null,null,null,null,null,null]},"1b304584-7904-11ee-9cb3-42010aa40fc0":{"n":2,"occ":[100,null,100,null,null,null,null,100,null,100,null,null,100,null,100,null,100,null,null,null,null,null,null,null]},"ae82196c-50fc-11f0-8cc3-42010aa400b8":{"n":4,"occ":[50,null,50,null,null,null,null,50,null,50,null,null,50,null,50,null,50,null,null,null,null,null,null,null]},"eeb4e022-6d38-11ee-a1f8-42010aa40fc0":{"n":2,"occ":[0,null,0,null,null,null,null,0,null,0,null,null,0,null,0,null,0,null,null,null,null,null,null,null]},"d6275236-7a6a-11ed-bb48-42010aa40fc0":{"n":2,"occ":[50,null,50,null,null,null,null,50,null,50,null,null,50,null,50,null,50,null,null,null,null,null,null,null]},"6bdf65b8-8529-11f0-ad08-42010aa400b8":{"n":2,"occ":[50,null,50,null,null,null,null,50,null,50,null,null,50,null,50,null,50,null,null,null,null,null,null,null]},"b3ea278c-ce88-11eb-8663-42010a840030":{"n":2,"occ":[0,null,0,null,null,null,null,0,null,0,null,null,0,null,0,null,0,null,null,null,null,null,null,null]},"5edaedf0-c7f1-11f0-b459-42010aa400b8":{"n":2,"occ":[0,null,0,null,null,null,null,0,null,0,null,null,0,null,0,null,0,null,null,null,null,null,null,null]},"NLLOC006880":{"n":2,"occ":[0,null,0,null,null,null,null,0,null,0,null,null,0,null,0,null,0,null,null,null,null,null,null,null]},"NLLOC004056":{"n":2,"occ":[50,null,50,null,null,null,null,50,null,0,null,null,0,null,50,null,100,null,null,null,null,null,null,null]},"NLLOC004253":{"n":2,"occ":[50,null,50,null,null,null,null,50,null,0,null,null,0,null,0,null,0,null,null,null,null,null,null,null]},"cc79e659-dd18-4fa2-9d01-23f456ec3b6b":{"n":2,"occ":[0,null,0,null,null,null,null,0,null,50,null,null,0,null,0,null,0,null,null,null,null,null,null,null]},"b3da1363-afb4-424f-93ad-4ec1fd57d75a":{"n":2,"occ":[50,null,50,null,null,null,null,50,null,50,null,null,50,null,100,null,100,null,null,null,null,null,null,null]},"3da0f551-73b5-4ab2-8a0c-adc6d06a5954":{"n":4,"occ":[25,null,25,null,null,null,null,25,null,25,null,null,0,null,0,null,0,null,null,null,null,null,null,null]},"NLLOC005481":{"n":2,"occ":[0,null,50,null,null,null,null,0,null,0,null,null,0,null,0,null,0,null,null,null,null,null,null,null]},"NLLOC001969":{"n":2,"occ":[0,null,0,null,null,null,null,0,null,0,null,null,0,null,0,null,0,null,null,null,null,null,null,null]},"fdf87ada-fa5e-4d86-86d0-39c30f77ca06":{"n":2,"occ":[0,null,0,null,null,null,null,0,null,0,null,null,0,null,0,null,0,null,null,null,null,null,null,null]},"66dab337d0d381001cd1cc35":{"n":2,"occ":[0,null,0,null,null,null,null,0,null,0,null,null,0,null,0,null,0,null,null,null,null,null,null,null]},"86df1f2aed14420369b1112ef85b70cd":{"n":2,"occ":[0,null,0,null,null,null,null,0,null,0,null,null,0,null,0,null,50,null,null,null,null,null,null,null]},"A7563936-10C2-4F97-B337-3ACAE07F63D5":{"n":2,"occ":[0,null,0,null,null,null,null,0,null,0,null,null,0,null,0,null,0,null,null,null,null,null,null,null]},"5425a725-6081-4acf-9c79-45d6a1918684":{"n":6,"occ":[33,null,33,null,null,null,null,17,null,17,null,null,0,null,17,null,33,null,null,null,null,null,null,null]},"NLLOC004058":{"n":2,"occ":[0,null,0,null,null,null,null,0,null,0,null,null,0,null,0,null,0,null,null,null,null,null,null,null]},"NLLOC009558":{"n":2,"occ":[0,null,0,null,null,null,null,0,null,0,null,null,50,null,50,null,0,null,null,null,null,null,null,null]},"66d9a2775c52bb001c27aa92":{"n":2,"occ":[0,null,0,null,null,null,null,0,null,0,null,null,0,null,0,null,0,null,null,null,null,null,null,null]},"NLLOC001968":{"n":2,"occ":[0,null,0,null,null,null,null,0,null,0,null,null,50,null,100,null,50,null,null,null,null,null,null,null]},"NLLOC002368":{"n":2,"occ":[50,null,100,null,null,null,null,100,null,100,null,null,100,null,100,null,50,null,null,null,null,null,null,null]},"NLLOC004357":{"n":2,"occ":[100,null,100,null,null,null,null,100,null,50,null,null,0,null,0,null,50,null,null,null,null,null,null,null]},"f8b6a561ae4fa994e4dc6b2d8a9e49a6":{"n":2,"occ":[50,null,50,null,null,null,null,50,null,50,null,null,0,null,0,null,50,null,null,null,null,null,null,null]},"NLLOC001922":{"n":2,"occ":[0,null,0,null,null,null,null,0,null,0,null,null,0,null,0,null,0,null,null,null,null,null,null,null]}}}