{"date":"2026-06-10","tz":"Europe/Amsterdam","locations":{"836":{"n":2,"occ":[null,50,null,null,null,null,50,null,null,null,50,null,null,null,0,null,null,null,50,null,null,null,null,null]},"1100":{"n":2,"occ":[null,0,null,null,null,null,0,null,null,null,0,null,null,null,0,null,null,null,50,null,null,null,null,null]},"1280":{"n":2,"occ":[null,50,null,null,null,null,50,null,null,null,0,null,null,null,0,null,null,null,0,null,null,null,null,null]},"1349":{"n":2,"occ":[null,100,null,null,null,null,100,null,null,null,0,null,null,null,50,null,null,null,100,null,null,null,null,null]},"1768":{"n":2,"occ":[null,50,null,null,null,null,50,null,null,null,50,null,null,null,50,null,null,null,50,null,null,null,null,null]},"1784":{"n":2,"occ":[null,100,null,null,null,null,100,null,null,null,50,null,null,null,50,null,null,null,100,null,null,null,null,null]},"1788":{"n":2,"occ":[null,50,null,null,null,null,50,null,null,null,0,null,null,null,50,null,null,null,0,null,null,null,null,null]},"1913":{"n":2,"occ":[null,100,null,null,null,null,100,null,null,null,50,null,null,null,50,null,null,null,100,null,null,null,null,null]},"17024ada-e079-11ed-827f-42010aa40fc0":{"n":21,"occ":[null,5,null,null,null,null,5,null,null,null,5,null,null,null,5,null,null,null,5,null,null,null,null,null]},"fcd27f8c-40ce-11f0-8930-42010aa400b8":{"n":2,"occ":[null,0,null,null,null,null,0,null,null,null,0,null,null,null,0,null,null,null,0,null,null,null,null,null]},"NLLOC002862":{"n":2,"occ":[null,0,null,null,null,null,0,null,null,null,50,null,null,null,50,null,null,null,0,null,null,null,null,null]},"4040fc22-c01c-11f0-a809-42010aa400b8":{"n":2,"occ":[null,50,null,null,null,null,50,null,null,null,50,null,null,null,50,null,null,null,50,null,null,null,null,null]},"NLLOC002302":{"n":2,"occ":[null,0,null,null,null,null,50,null,null,null,50,null,null,null,0,null,null,null,0,null,null,null,null,null]},"NLLOC008777":{"n":2,"occ":[null,50,null,null,null,null,50,null,null,null,0,null,null,null,0,null,null,null,50,null,null,null,null,null]},"5eb722e0-4f88-11ea-9cb5-42010a840003":{"n":2,"occ":[null,0,null,null,null,null,0,null,null,null,0,null,null,null,0,null,null,null,0,null,null,null,null,null]},"cef59abc-4f3c-11e8-a227-42010a840002":{"n":2,"occ":[null,0,null,null,null,null,0,null,null,null,0,null,null,null,0,null,null,null,0,null,null,null,null,null]},"NLLOC003483":{"n":2,"occ":[null,50,null,null,null,null,50,null,null,null,0,null,null,null,0,null,null,null,100,null,null,null,null,null]},"d95f5f9e-f94c-11ef-be36-42010aa400b8":{"n":2,"occ":[null,0,null,null,null,null,0,null,null,null,0,null,null,null,0,null,null,null,0,null,null,null,null,null]},"e769042c-b9d2-11f0-afa7-42010aa400b8":{"n":2,"occ":[null,0,null,null,null,null,0,null,null,null,0,null,null,null,0,null,null,null,0,null,null,null,null,null]},"5959563c-f92a-4fff-849d-ca3a92541430":{"n":21,"occ":[null,0,null,null,null,null,0,null,null,null,14,null,null,null,19,null,null,null,14,null,null,null,null,null]},"1a15d4be-ca53-11f0-a491-42010aa400b8":{"n":2,"occ":[null,0,null,null,null,null,0,null,null,null,0,null,null,null,0,null,null,null,0,null,null,null,null,null]},"790dc9f8-7a97-11ee-84ad-42010aa40fc0":{"n":2,"occ":[null,0,null,null,null,null,0,null,null,null,0,null,null,null,0,null,null,null,0,null,null,null,null,null]},"5e2b46ac-363a-11e9-bcfa-42010a840003":{"n":2,"occ":[null,0,null,null,null,null,0,null,null,null,0,null,null,null,0,null,null,null,0,null,null,null,null,null]},"4e5f8d8c-ca53-11f0-a4e8-42010aa400b8":{"n":2,"occ":[null,0,null,null,null,null,0,null,null,null,0,null,null,null,0,null,null,null,0,null,null,null,null,null]},"NLLOC002718":{"n":2,"occ":[null,50,null,null,null,null,50,null,null,null,0,null,null,null,0,null,null,null,0,null,null,null,null,null]},"afd9509a-1644-4720-bff7-c0638b9cab61":{"n":2,"occ":[null,100,null,null,null,null,0,null,null,null,0,null,null,null,0,null,null,null,0,null,null,null,null,null]},"d31bf5e0-1179-11ef-b548-42010aa400b8":{"n":2,"occ":[null,0,null,null,null,null,0,null,null,null,0,null,null,null,0,null,null,null,0,null,null,null,null,null]},"daee73d8-c3dc-11ed-8315-42010aa40fcb":{"n":2,"occ":[null,0,null,null,null,null,0,null,null,null,0,null,null,null,0,null,null,null,0,null,null,null,null,null]},"20bbf6e8-3761-11f0-8dcf-42010aa400b8":{"n":2,"occ":[null,50,null,null,null,null,50,null,null,null,50,null,null,null,50,null,null,null,50,null,null,null,null,null]},"99063ad0-7a25-11f0-a46c-42010aa400b8":{"n":2,"occ":[null,0,null,null,null,null,0,null,null,null,0,null,null,null,0,null,null,null,0,null,null,null,null,null]},"e29e7780-58ca-11ee-8cd7-42010aa40fc0":{"n":2,"occ":[null,0,null,null,null,null,0,null,null,null,0,null,null,null,0,null,null,null,0,null,null,null,null,null]},"009aa6c2-5665-11e9-9061-42010a840003":{"n":2,"occ":[null,0,null,null,null,null,0,null,null,null,0,null,null,null,0,null,null,null,0,null,null,null,null,null]},"NLLOC002864":{"n":2,"occ":[null,0,null,null,null,null,0,null,null,null,50,null,null,null,50,null,null,null,50,null,null,null,null,null]},"7d82f05a-d653-11e8-b336-42010a840002":{"n":2,"occ":[null,100,null,null,null,null,100,null,null,null,100,null,null,null,100,null,null,null,100,null,null,null,null,null]},"87c30cb6-363a-11e9-a439-42010a840003":{"n":2,"occ":[null,0,null,null,null,null,0,null,null,null,0,null,null,null,0,null,null,null,0,null,null,null,null,null]},"cbd7eac4-4f3c-11e8-bae4-42010a840002":{"n":2,"occ":[null,50,null,null,null,null,50,null,null,null,50,null,null,null,50,null,null,null,50,null,null,null,null,null]},"dc7790c8-4f3c-11e8-b007-42010a840002":{"n":2,"occ":[null,50,null,null,null,null,50,null,null,null,50,null,null,null,50,null,null,null,50,null,null,null,null,null]},"5c3ebda2-f3f6-11f0-83c5-42010aa400b8":{"n":2,"occ":[null,0,null,null,null,null,0,null,null,null,0,null,null,null,0,null,null,null,0,null,null,null,null,null]},"NLLOC004851":{"n":2,"occ":[null,100,null,null,null,null,100,null,null,null,0,null,null,null,50,null,null,null,50,null,null,null,null,null]},"6f7d00115af011919cbcaafca6e8721e":{"n":2,"occ":[null,0,null,null,null,null,0,null,null,null,50,null,null,null,50,null,null,null,0,null,null,null,null,null]},"c339ba64-75ac-11e8-98de-42010a840002":{"n":2,"occ":[null,50,null,null,null,null,50,null,null,null,50,null,null,null,50,null,null,null,50,null,null,null,null,null]},"f0623570-4be9-11e9-a0d4-42010a840003":{"n":2,"occ":[null,0,null,null,null,null,0,null,null,null,0,null,null,null,0,null,null,null,0,null,null,null,null,null]},"fd133458-b879-11e8-8a7e-42010a840002":{"n":2,"occ":[null,50,null,null,null,null,50,null,null,null,50,null,null,null,50,null,null,null,50,null,null,null,null,null]},"cea145ac-4f3c-11e8-99f9-42010a840002":{"n":2,"occ":[null,50,null,null,null,null,50,null,null,null,50,null,null,null,50,null,null,null,50,null,null,null,null,null]},"5571532c-9930-11e9-ac90-42010a840003":{"n":2,"occ":[null,0,null,null,null,null,0,null,null,null,0,null,null,null,0,null,null,null,0,null,null,null,null,null]},"82c5afca-d67b-11e9-b52a-42010a840003":{"n":2,"occ":[null,100,null,null,null,null,100,null,null,null,100,null,null,null,100,null,null,null,100,null,null,null,null,null]},"2F02F3E4-443D-4978-9C6B-F70223665F06":{"n":2,"occ":[null,100,null,null,null,null,100,null,null,null,100,null,null,null,100,null,null,null,100,null,null,null,null,null]},"4fd27d3c-1d6a-11eb-b3dd-42010a840003":{"n":2,"occ":[null,100,null,null,null,null,100,null,null,null,100,null,null,null,100,null,null,null,100,null,null,null,null,null]},"487b5c8c-9479-11e9-bea4-42010a840003":{"n":2,"occ":[null,50,null,null,null,null,50,null,null,null,50,null,null,null,50,null,null,null,50,null,null,null,null,null]},"9c636f00-cd76-11f0-9ef7-42010aa400b8":{"n":2,"occ":[null,0,null,null,null,null,0,null,null,null,0,null,null,null,0,null,null,null,0,null,null,null,null,null]},"1feafa6a-bb65-11f0-b165-42010aa400b8":{"n":2,"occ":[null,0,null,null,null,null,0,null,null,null,0,null,null,null,0,null,null,null,0,null,null,null,null,null]},"9a7e856a-fd09-11ee-b9ee-42010aa400b8":{"n":2,"occ":[null,0,null,null,null,null,0,null,null,null,0,null,null,null,0,null,null,null,0,null,null,null,null,null]},"a87c3fe2-324b-11ee-807a-42010aa40fc0":{"n":2,"occ":[null,50,null,null,null,null,50,null,null,null,50,null,null,null,50,null,null,null,50,null,null,null,null,null]},"aff086ee-c65e-11f0-8832-42010aa400b8":{"n":2,"occ":[null,0,null,null,null,null,0,null,null,null,0,null,null,null,0,null,null,null,0,null,null,null,null,null]},"4bbfd1d2-6747-11eb-9285-42010a840003":{"n":2,"occ":[null,50,null,null,null,null,50,null,null,null,50,null,null,null,50,null,null,null,50,null,null,null,null,null]},"0f020cf4-d3f8-11e8-8003-42010a840002":{"n":2,"occ":[null,100,null,null,null,null,100,null,null,null,100,null,null,null,100,null,null,null,100,null,null,null,null,null]},"82d05b28-d67b-11e9-ae7e-42010a840003":{"n":2,"occ":[null,0,null,null,null,null,0,null,null,null,0,null,null,null,0,null,null,null,0,null,null,null,null,null]},"a75d7a3c-ad7a-11e8-8a89-42010a840002":{"n":2,"occ":[null,50,null,null,null,null,50,null,null,null,50,null,null,null,50,null,null,null,50,null,null,null,null,null]},"56c80c6c-cc6b-11ed-9749-42010aa40029":{"n":2,"occ":[null,0,null,null,null,null,0,null,null,null,0,null,null,null,0,null,null,null,0,null,null,null,null,null]},"87696958-4d01-11ee-bd28-42010aa40fc0":{"n":2,"occ":[null,0,null,null,null,null,0,null,null,null,0,null,null,null,0,null,null,null,0,null,null,null,null,null]},"fa894c5c-8529-11f0-8916-42010aa400b8":{"n":2,"occ":[null,0,null,null,null,null,0,null,null,null,0,null,null,null,0,null,null,null,0,null,null,null,null,null]},"NLLOC002324":{"n":2,"occ":[null,50,null,null,null,null,0,null,null,null,0,null,null,null,0,null,null,null,50,null,null,null,null,null]},"NLLOC002321":{"n":2,"occ":[null,100,null,null,null,null,50,null,null,null,0,null,null,null,50,null,null,null,100,null,null,null,null,null]},"NLLOC003474":{"n":2,"occ":[null,50,null,null,null,null,50,null,null,null,0,null,null,null,0,null,null,null,0,null,null,null,null,null]},"BF19E908-57CE-46BA-AE0F-AFF454BE4F78":{"n":2,"occ":[null,50,null,null,null,null,0,null,null,null,0,null,null,null,0,null,null,null,0,null,null,null,null,null]},"ACD8B227-D596-4AD7-817F-BB97217C1632":{"n":2,"occ":[null,50,null,null,null,null,50,null,null,null,50,null,null,null,50,null,null,null,50,null,null,null,null,null]},"NLLOC012100":{"n":2,"occ":[null,50,null,null,null,null,50,null,null,null,0,null,null,null,50,null,null,null,0,null,null,null,null,null]},"NLLOC002516":{"n":2,"occ":[null,50,null,null,null,null,50,null,null,null,0,null,null,null,0,null,null,null,0,null,null,null,null,null]},"22EE7120-CB96-4D07-8A15-DD064898F780":{"n":2,"occ":[null,50,null,null,null,null,100,null,null,null,100,null,null,null,100,null,null,null,100,null,null,null,null,null]},"B2311E3D-E12F-4E74-98A7-81EECB2B8A58":{"n":2,"occ":[null,50,null,null,null,null,50,null,null,null,50,null,null,null,50,null,null,null,50,null,null,null,null,null]},"A585486E-2E2F-4174-B0E7-56A442107BE9":{"n":2,"occ":[null,0,null,null,null,null,0,null,null,null,0,null,null,null,0,null,null,null,0,null,null,null,null,null]},"NLLOC004297":{"n":2,"occ":[null,0,null,null,null,null,0,null,null,null,0,null,null,null,0,null,null,null,0,null,null,null,null,null]},"10DAD4A7-3435-48A3-BF96-432D6944FE3B":{"n":2,"occ":[null,0,null,null,null,null,100,null,null,null,100,null,null,null,100,null,null,null,100,null,null,null,null,null]},"NLLOC002274":{"n":2,"occ":[null,0,null,null,null,null,0,null,null,null,0,null,null,null,0,null,null,null,0,null,null,null,null,null]},"AA36379D-ECBE-4313-AA98-220FEB84B933":{"n":2,"occ":[null,100,null,null,null,null,100,null,null,null,100,null,null,null,100,null,null,null,100,null,null,null,null,null]},"NLLOC003591":{"n":2,"occ":[null,100,null,null,null,null,100,null,null,null,50,null,null,null,50,null,null,null,0,null,null,null,null,null]},"9257666d-cd17-4007-8494-428cf09c3ece":{"n":2,"occ":[null,0,null,null,null,null,0,null,null,null,0,null,null,null,0,null,null,null,0,null,null,null,null,null]},"318103fae5257c8ac7b604ab2730c384":{"n":2,"occ":[null,100,null,null,null,null,50,null,null,null,50,null,null,null,50,null,null,null,100,null,null,null,null,null]},"NLLOC002694":{"n":2,"occ":[null,100,null,null,null,null,100,null,null,null,50,null,null,null,50,null,null,null,50,null,null,null,null,null]},"NLLOC004328":{"n":2,"occ":[null,100,null,null,null,null,100,null,null,null,50,null,null,null,0,null,null,null,100,null,null,null,null,null]},"6442B2AB-A73B-4B0F-ADC0-A66A717DF0B5":{"n":2,"occ":[null,50,null,null,null,null,100,null,null,null,100,null,null,null,100,null,null,null,100,null,null,null,null,null]},"NLLOC004857":{"n":2,"occ":[null,0,null,null,null,null,0,null,null,null,0,null,null,null,0,null,null,null,0,null,null,null,null,null]},"a78d3efc-a030-4aad-94c6-59a3171b7bf4":{"n":2,"occ":[null,50,null,null,null,null,50,null,null,null,0,null,null,null,0,null,null,null,50,null,null,null,null,null]},"NLLOC003700":{"n":2,"occ":[null,0,null,null,null,null,0,null,null,null,50,null,null,null,0,null,null,null,0,null,null,null,null,null]},"NLLOC007724":{"n":2,"occ":[null,0,null,null,null,null,0,null,null,null,50,null,null,null,0,null,null,null,100,null,null,null,null,null]},"f1284867-6abc-4b5c-bb9b-cd2485ddd92e":{"n":2,"occ":[null,0,null,null,null,null,0,null,null,null,0,null,null,null,0,null,null,null,0,null,null,null,null,null]},"68779fb2d0c6f408e08a6c02":{"n":1,"occ":[null,0,null,null,null,null,0,null,null,null,0,null,null,null,0,null,null,null,0,null,null,null,null,null]}}}