{"date":"2026-06-13","tz":"Europe/Amsterdam","locations":{"28":{"n":2,"occ":[null,50,null,null,null,null,50,null,null,null,50,null,null,100,null,null,100,null,100,null,null,null,null,null]},"31800":{"n":2,"occ":[null,0,null,null,null,null,0,null,null,null,0,null,null,0,null,null,0,null,0,null,null,null,null,null]},"50859":{"n":4,"occ":[null,25,null,null,null,null,0,null,null,null,50,null,null,75,null,null,50,null,0,null,null,null,null,null]},"50924":{"n":8,"occ":[null,0,null,null,null,null,13,null,null,null,38,null,null,25,null,null,25,null,25,null,null,null,null,null]},"2679353":{"n":1,"occ":[null,0,null,null,null,null,0,null,null,null,0,null,null,0,null,null,0,null,0,null,null,null,null,null]},"2700106":{"n":4,"occ":[null,0,null,null,null,null,0,null,null,null,0,null,null,0,null,null,0,null,0,null,null,null,null,null]},"3455950":{"n":6,"occ":[null,0,null,null,null,null,0,null,null,null,0,null,null,0,null,null,0,null,0,null,null,null,null,null]},"4227578":{"n":6,"occ":[null,17,null,null,null,null,17,null,null,null,17,null,null,17,null,null,17,null,17,null,null,null,null,null]},"4613557":{"n":1,"occ":[null,0,null,null,null,null,0,null,null,null,0,null,null,0,null,null,0,null,0,null,null,null,null,null]},"80269410":{"n":2,"occ":[null,0,null,null,null,null,0,null,null,null,0,null,null,0,null,null,0,null,0,null,null,null,null,null]},"faf2e0fbf5927861ce0a476290fcb567":{"n":1,"occ":[null,0,null,null,null,null,0,null,null,null,0,null,null,0,null,null,0,null,100,null,null,null,null,null]},"NLLOC008143":{"n":2,"occ":[null,0,null,null,null,null,0,null,null,null,0,null,null,0,null,null,0,null,0,null,null,null,null,null]},"NLLOC003998":{"n":2,"occ":[null,0,null,null,null,null,0,null,null,null,100,null,null,50,null,null,100,null,50,null,null,null,null,null]},"cf423598-f0ba-11f0-8364-42010aa400b8":{"n":6,"occ":[null,50,null,null,null,null,50,null,null,null,50,null,null,50,null,null,50,null,50,null,null,null,null,null]},"2b16b7fa-63b3-11ee-b739-42010aa40fc0":{"n":2,"occ":[null,0,null,null,null,null,0,null,null,null,0,null,null,0,null,null,0,null,0,null,null,null,null,null]},"4fdf1e5c-b0ce-11ee-afd8-42010aa40fc0":{"n":2,"occ":[null,0,null,null,null,null,0,null,null,null,0,null,null,0,null,null,0,null,0,null,null,null,null,null]},"NLLOC014017":{"n":2,"occ":[null,50,null,null,null,null,50,null,null,null,50,null,null,0,null,null,50,null,100,null,null,null,null,null]},"66E9444B-344D-48DD-9C09-F98D311E8617":{"n":6,"occ":[null,0,null,null,null,null,0,null,null,null,0,null,null,0,null,null,0,null,0,null,null,null,null,null]},"63457fdf26fb53b2c001395f":{"n":1,"occ":[null,0,null,null,null,null,0,null,null,null,0,null,null,0,null,null,0,null,100,null,null,null,null,null]},"5ae180f0-4f3c-11e8-959d-42010a840002":{"n":2,"occ":[null,50,null,null,null,null,50,null,null,null,50,null,null,50,null,null,50,null,50,null,null,null,null,null]},"ca72fd20-52ac-11ea-8ce3-42010a840003":{"n":2,"occ":[null,0,null,null,null,null,0,null,null,null,0,null,null,0,null,null,0,null,0,null,null,null,null,null]},"NLLOC018890":{"n":2,"occ":[null,0,null,null,null,null,0,null,null,null,0,null,null,50,null,null,0,null,0,null,null,null,null,null]},"b201e316-1771-11eb-8d2f-42010a840037":{"n":4,"occ":[null,25,null,null,null,null,25,null,null,null,25,null,null,25,null,null,25,null,25,null,null,null,null,null]},"66951e91016a0f001c74cd50":{"n":2,"occ":[null,50,null,null,null,null,50,null,null,null,50,null,null,50,null,null,50,null,50,null,null,null,null,null]},"e3d94dc3a2b0dc9614d680426bf34d2c":{"n":6,"occ":[null,17,null,null,null,null,17,null,null,null,17,null,null,17,null,null,0,null,0,null,null,null,null,null]},"7e320cb8-a15a-11ec-975f-42010a840003":{"n":2,"occ":[null,50,null,null,null,null,50,null,null,null,50,null,null,50,null,null,50,null,50,null,null,null,null,null]},"e352a3a2-71e5-11e9-9192-42010a840003":{"n":2,"occ":[null,0,null,null,null,null,0,null,null,null,0,null,null,0,null,null,0,null,0,null,null,null,null,null]},"b2df1416-417e-11f0-8027-42010aa400b8":{"n":2,"occ":[null,0,null,null,null,null,0,null,null,null,0,null,null,0,null,null,0,null,0,null,null,null,null,null]},"a3ae6596-6ede-11ef-b537-42010aa400b8":{"n":2,"occ":[null,0,null,null,null,null,0,null,null,null,0,null,null,0,null,null,0,null,0,null,null,null,null,null]},"0738e08b-c2b5-40d1-800f-7855ea421449":{"n":3,"occ":[null,0,null,null,null,null,0,null,null,null,0,null,null,0,null,null,0,null,0,null,null,null,null,null]},"45ad0474-ebda-11ea-8f74-42010a840003":{"n":2,"occ":[null,0,null,null,null,null,0,null,null,null,0,null,null,0,null,null,0,null,0,null,null,null,null,null]},"NLLOC006987":{"n":2,"occ":[null,0,null,null,null,null,0,null,null,null,0,null,null,50,null,null,50,null,50,null,null,null,null,null]},"NLLOC006191":{"n":2,"occ":[null,50,null,null,null,null,50,null,null,null,50,null,null,100,null,null,100,null,100,null,null,null,null,null]},"e0bbecde-71e5-11e9-8135-42010a840003":{"n":2,"occ":[null,50,null,null,null,null,50,null,null,null,50,null,null,50,null,null,50,null,50,null,null,null,null,null]},"2fae87b5-fa5a-4aa5-a784-4a1154a9159b":{"n":2,"occ":[null,50,null,null,null,null,50,null,null,null,0,null,null,0,null,null,50,null,50,null,null,null,null,null]},"43ba28ac-1866-4c3b-83d5-05181e0eb4ea":{"n":2,"occ":[null,100,null,null,null,null,100,null,null,null,100,null,null,0,null,null,0,null,0,null,null,null,null,null]},"e9c206b0-571e-11ee-872e-42010aa40fc0":{"n":4,"occ":[null,100,null,null,null,null,100,null,null,null,100,null,null,100,null,null,100,null,100,null,null,null,null,null]},"32068082-63b2-11ee-92f9-42010aa40fc0":{"n":5,"occ":[null,20,null,null,null,null,20,null,null,null,20,null,null,20,null,null,20,null,20,null,null,null,null,null]},"dd92a410-fdb5-11ee-9bde-42010aa400b8":{"n":8,"occ":[null,75,null,null,null,null,75,null,null,null,75,null,null,75,null,null,75,null,75,null,null,null,null,null]},"55aa5352-a131-11ea-9007-42010a840003":{"n":2,"occ":[null,50,null,null,null,null,50,null,null,null,50,null,null,50,null,null,50,null,50,null,null,null,null,null]},"6498e712-50a5-11e9-9dd7-42010a840003":{"n":2,"occ":[null,100,null,null,null,null,100,null,null,null,100,null,null,100,null,null,100,null,100,null,null,null,null,null]},"d8f24674-e6c7-11ec-8321-42010aa40fc0":{"n":2,"occ":[null,0,null,null,null,null,0,null,null,null,0,null,null,0,null,null,0,null,0,null,null,null,null,null]},"33d1ce2d963140ecb8b90420e32aeb16":{"n":6,"occ":[null,0,null,null,null,null,0,null,null,null,0,null,null,0,null,null,0,null,0,null,null,null,null,null]},"6345802526fb537a35014606":{"n":1,"occ":[null,0,null,null,null,null,0,null,null,null,0,null,null,0,null,null,0,null,0,null,null,null,null,null]},"7cd6b90e-527f-11e9-a763-42010a840003":{"n":2,"occ":[null,0,null,null,null,null,0,null,null,null,0,null,null,0,null,null,0,null,0,null,null,null,null,null]},"e067c4ff-3b01-439a-af30-d695e9fd5bd0":{"n":2,"occ":[null,50,null,null,null,null,50,null,null,null,50,null,null,0,null,null,0,null,0,null,null,null,null,null]},"960e2bd8-d54e-11eb-89aa-42010a840003":{"n":2,"occ":[null,0,null,null,null,null,0,null,null,null,0,null,null,0,null,null,0,null,0,null,null,null,null,null]},"91b7754e641dfe0d7fccf950799b820a":{"n":2,"occ":[null,100,null,null,null,null,100,null,null,null,50,null,null,50,null,null,50,null,50,null,null,null,null,null]},"43cf70d4-4d93-11e8-83b2-42010a840002":{"n":2,"occ":[null,0,null,null,null,null,0,null,null,null,0,null,null,0,null,null,0,null,0,null,null,null,null,null]},"14740532-9e4b-11eb-8fdc-42010a840003":{"n":2,"occ":[null,0,null,null,null,null,0,null,null,null,0,null,null,0,null,null,0,null,0,null,null,null,null,null]},"5ae8d83c-4f3c-11e8-a721-42010a840002":{"n":2,"occ":[null,100,null,null,null,null,100,null,null,null,100,null,null,100,null,null,100,null,100,null,null,null,null,null]},"63a1b291eb74e50012653600":{"n":1,"occ":[null,0,null,null,null,null,0,null,null,null,0,null,null,0,null,null,0,null,0,null,null,null,null,null]},"NLLOC003663":{"n":2,"occ":[null,50,null,null,null,null,50,null,null,null,50,null,null,50,null,null,0,null,50,null,null,null,null,null]},"433f818c-9993-11eb-b330-42010a840003":{"n":2,"occ":[null,0,null,null,null,null,0,null,null,null,0,null,null,0,null,null,0,null,0,null,null,null,null,null]},"9179106c-ef41-11eb-a901-42010a840003":{"n":2,"occ":[null,0,null,null,null,null,0,null,null,null,0,null,null,0,null,null,0,null,0,null,null,null,null,null]},"c86420e6-b0e8-11ea-9042-42010a840003":{"n":2,"occ":[null,50,null,null,null,null,50,null,null,null,50,null,null,50,null,null,50,null,50,null,null,null,null,null]},"17a71733-862a-4519-a629-58e209ab7448":{"n":2,"occ":[null,0,null,null,null,null,0,null,null,null,0,null,null,0,null,null,0,null,0,null,null,null,null,null]},"792fb4ec-88cb-11ec-aa7c-42010a840003":{"n":2,"occ":[null,0,null,null,null,null,0,null,null,null,0,null,null,0,null,null,0,null,0,null,null,null,null,null]},"e79385e6-e210-11ec-ac3c-42010aa40fc0":{"n":2,"occ":[null,0,null,null,null,null,0,null,null,null,0,null,null,0,null,null,0,null,0,null,null,null,null,null]},"13f9ffaa-21b4-11ee-b0e5-42010aa40fc0":{"n":2,"occ":[null,50,null,null,null,null,50,null,null,null,50,null,null,50,null,null,50,null,50,null,null,null,null,null]},"3bb2416a-15c2-11ec-9c48-42010a840003":{"n":2,"occ":[null,50,null,null,null,null,50,null,null,null,50,null,null,50,null,null,50,null,50,null,null,null,null,null]},"5a8d645c-4f3c-11e8-9d65-42010a840002":{"n":2,"occ":[null,100,null,null,null,null,100,null,null,null,100,null,null,100,null,null,100,null,100,null,null,null,null,null]},"d3feb0f8-ac31-11ea-b02d-42010a840003":{"n":2,"occ":[null,0,null,null,null,null,0,null,null,null,0,null,null,0,null,null,0,null,0,null,null,null,null,null]},"69e9f4fd34abdaebb4001706":{"n":1,"occ":[null,0,null,null,null,null,0,null,null,null,0,null,null,0,null,null,0,null,0,null,null,null,null,null]},"42414928-3AD0-4504-A9D6-E1CE3452097F":{"n":5,"occ":[null,20,null,null,null,null,20,null,null,null,40,null,null,40,null,null,0,null,40,null,null,null,null,null]},"NLLOC008463":{"n":2,"occ":[null,0,null,null,null,null,0,null,null,null,0,null,null,0,null,null,0,null,0,null,null,null,null,null]},"29e5f4b2-51d8-4c44-b9c1-a6fe7ba69c22":{"n":2,"occ":[null,50,null,null,null,null,50,null,null,null,0,null,null,0,null,null,50,null,50,null,null,null,null,null]},"e9a79707f6c473a284870fb0324f69f1":{"n":2,"occ":[null,50,null,null,null,null,50,null,null,null,50,null,null,0,null,null,0,null,0,null,null,null,null,null]},"e5e1715c-f67e-40ee-9998-00ebae49fb19":{"n":2,"occ":[null,0,null,null,null,null,0,null,null,null,0,null,null,0,null,null,0,null,0,null,null,null,null,null]},"66a0e118c33d2f001c553073":{"n":2,"occ":[null,0,null,null,null,null,0,null,null,null,0,null,null,0,null,null,0,null,0,null,null,null,null,null]},"7c84ba28-978e-48d8-8bc6-a75948d1fc9a":{"n":2,"occ":[null,0,null,null,null,null,0,null,null,null,0,null,null,0,null,null,0,null,0,null,null,null,null,null]},"68eef9d2-5d2e-453b-806e-b38dc42c5085":{"n":2,"occ":[null,100,null,null,null,null,100,null,null,null,50,null,null,0,null,null,0,null,50,null,null,null,null,null]},"cb61708cb197d6e63defd594f25b9d08":{"n":2,"occ":[null,50,null,null,null,null,50,null,null,null,0,null,null,50,null,null,0,null,0,null,null,null,null,null]},"NLLOC013351":{"n":2,"occ":[null,0,null,null,null,null,0,null,null,null,0,null,null,50,null,null,0,null,0,null,null,null,null,null]},"61853dbd6f10eec3d2aa0ae8":{"n":1,"occ":[null,0,null,null,null,null,0,null,null,null,0,null,null,0,null,null,0,null,0,null,null,null,null,null]},"cfd1fa609d4e3d761067914644c00eb0":{"n":1,"occ":[null,0,null,null,null,null,0,null,null,null,0,null,null,0,null,null,0,null,0,null,null,null,null,null]},"9d19173a-08e9-11eb-bc51-42010a840033":{"n":2,"occ":[null,0,null,null,null,null,0,null,null,null,0,null,null,0,null,null,0,null,0,null,null,null,null,null]},"6412d67c02001c00128c4889":{"n":2,"occ":[null,0,null,null,null,null,0,null,null,null,0,null,null,0,null,null,0,null,0,null,null,null,null,null]},"661d379f350ad2001c43fcb5":{"n":1,"occ":[null,100,null,null,null,null,100,null,null,null,100,null,null,100,null,null,100,null,100,null,null,null,null,null]},"ce284060-b87d-4714-870b-1db6f876b78b":{"n":2,"occ":[null,50,null,null,null,null,50,null,null,null,0,null,null,50,null,null,50,null,50,null,null,null,null,null]},"66951204b08204001ca58d14":{"n":2,"occ":[null,0,null,null,null,null,0,null,null,null,0,null,null,50,null,null,50,null,0,null,null,null,null,null]},"68632786f3bbb626c4cacd3302dcd39e":{"n":2,"occ":[null,100,null,null,null,null,100,null,null,null,100,null,null,0,null,null,0,null,50,null,null,null,null,null]},"ebdd7b3335dc261b1811bd6374db17de":{"n":2,"occ":[null,0,null,null,null,null,0,null,null,null,0,null,null,0,null,null,50,null,50,null,null,null,null,null]},"73a86611-b556-462a-915d-1f5872e0f442":{"n":2,"occ":[null,0,null,null,null,null,0,null,null,null,0,null,null,0,null,null,0,null,0,null,null,null,null,null]},"NLLOC014399":{"n":2,"occ":[null,0,null,null,null,null,0,null,null,null,50,null,null,50,null,null,100,null,100,null,null,null,null,null]},"9CBDDB91-DC42-4818-B888-99B698C79AFC":{"n":4,"occ":[null,25,null,null,null,null,25,null,null,null,25,null,null,50,null,null,25,null,25,null,null,null,null,null]},"661d373af0b021001c53dea8":{"n":1,"occ":[null,0,null,null,null,null,100,null,null,null,100,null,null,100,null,null,100,null,100,null,null,null,null,null]},"6802397e5b84405bc2bd302d":{"n":2,"occ":[null,50,null,null,null,null,50,null,null,null,50,null,null,0,null,null,0,null,0,null,null,null,null,null]},"66a0f79737ba79001c6010a4":{"n":2,"occ":[null,0,null,null,null,null,0,null,null,null,0,null,null,0,null,null,0,null,50,null,null,null,null,null]},"NLLOC018859":{"n":2,"occ":[null,0,null,null,null,null,0,null,null,null,50,null,null,50,null,null,0,null,0,null,null,null,null,null]},"1b65d9d7-76b1-448a-b3f5-17c79108b68d":{"n":2,"occ":[null,50,null,null,null,null,50,null,null,null,0,null,null,0,null,null,0,null,0,null,null,null,null,null]},"64a342df6da8db001c75a600":{"n":1,"occ":[null,0,null,null,null,null,0,null,null,null,0,null,null,0,null,null,0,null,0,null,null,null,null,null]},"a278da93991e4b19f138766b8d643e23":{"n":2,"occ":[null,0,null,null,null,null,0,null,null,null,0,null,null,0,null,null,0,null,0,null,null,null,null,null]},"691b5254-0377-4b20-ab29-e2c4e9759ee1":{"n":2,"occ":[null,100,null,null,null,null,100,null,null,null,0,null,null,0,null,null,50,null,50,null,null,null,null,null]},"6069b465d72bcb2c494e6cf0ccd362be":{"n":2,"occ":[null,100,null,null,null,null,100,null,null,null,100,null,null,0,null,null,0,null,100,null,null,null,null,null]},"691333b53ca31db54bed5e59":{"n":1,"occ":[null,0,null,null,null,null,0,null,null,null,0,null,null,0,null,null,0,null,0,null,null,null,null,null]},"c8beb6d0-6002-4686-bb88-dcf806c487ab":{"n":2,"occ":[null,0,null,null,null,null,0,null,null,null,0,null,null,50,null,null,50,null,0,null,null,null,null,null]},"ED654FF0-57BA-4850-82F3-8E556D1050AD":{"n":2,"occ":[null,0,null,null,null,null,0,null,null,null,0,null,null,0,null,null,0,null,0,null,null,null,null,null]},"664762056160c7001cf1a876":{"n":2,"occ":[null,0,null,null,null,null,0,null,null,null,0,null,null,50,null,null,50,null,0,null,null,null,null,null]},"NLLOC023901":{"n":2,"occ":[null,0,null,null,null,null,0,null,null,null,0,null,null,0,null,null,0,null,0,null,null,null,null,null]},"NLLOC003252":{"n":2,"occ":[null,0,null,null,null,null,0,null,null,null,0,null,null,0,null,null,0,null,0,null,null,null,null,null]},"735522c5-252c-46e3-80a0-0b72d3c54c32":{"n":2,"occ":[null,50,null,null,null,null,50,null,null,null,50,null,null,100,null,null,50,null,100,null,null,null,null,null]},"60c220a67419b64ce5d3f447":{"n":1,"occ":[null,0,null,null,null,null,0,null,null,null,0,null,null,0,null,null,0,null,0,null,null,null,null,null]},"698dd8d32e2224470df8db4a":{"n":1,"occ":[null,0,null,null,null,null,0,null,null,null,0,null,null,0,null,null,0,null,0,null,null,null,null,null]},"661d37f5f0b021001c53e99c":{"n":1,"occ":[null,0,null,null,null,null,0,null,null,null,0,null,null,0,null,null,0,null,0,null,null,null,null,null]},"NLLOC003659":{"n":2,"occ":[null,0,null,null,null,null,0,null,null,null,0,null,null,0,null,null,0,null,0,null,null,null,null,null]},"NLLOC015380":{"n":2,"occ":[null,0,null,null,null,null,0,null,null,null,0,null,null,0,null,null,0,null,0,null,null,null,null,null]},"9c1a5edc6430b7b9a1f18707d56050c6":{"n":2,"occ":[null,0,null,null,null,null,0,null,null,null,0,null,null,0,null,null,50,null,0,null,null,null,null,null]},"6e7ea360424a5643f291f2ea71508a2d":{"n":2,"occ":[null,0,null,null,null,null,0,null,null,null,0,null,null,0,null,null,50,null,50,null,null,null,null,null]},"661d25d11e629c001c0919f9":{"n":1,"occ":[null,0,null,null,null,null,0,null,null,null,0,null,null,0,null,null,0,null,0,null,null,null,null,null]},"NLLOC019526":{"n":2,"occ":[null,0,null,null,null,null,0,null,null,null,0,null,null,0,null,null,0,null,0,null,null,null,null,null]},"660d4906653922001c93065e":{"n":4,"occ":[null,25,null,null,null,null,25,null,null,null,25,null,null,25,null,null,25,null,0,null,null,null,null,null]},"NLLOC007359":{"n":2,"occ":[null,50,null,null,null,null,50,null,null,null,50,null,null,0,null,null,0,null,0,null,null,null,null,null]},"NLLOC000659":{"n":2,"occ":[null,0,null,null,null,null,0,null,null,null,50,null,null,100,null,null,0,null,0,null,null,null,null,null]},"63d7eaf81dbfa60012d91aa8":{"n":2,"occ":[null,0,null,null,null,null,0,null,null,null,0,null,null,0,null,null,0,null,0,null,null,null,null,null]},"63f8b539bc8e1b0012b4f20b":{"n":1,"occ":[null,0,null,null,null,null,0,null,null,null,0,null,null,0,null,null,0,null,0,null,null,null,null,null]},"67c97a86a6e441e5e35f078b":{"n":2,"occ":[null,0,null,null,null,null,0,null,null,null,0,null,null,0,null,null,0,null,0,null,null,null,null,null]},"NLLOC013226":{"n":2,"occ":[null,0,null,null,null,null,0,null,null,null,0,null,null,50,null,null,0,null,0,null,null,null,null,null]},"02e6cb029555d1e24fc02f38e75e1343":{"n":2,"occ":[null,50,null,null,null,null,0,null,null,null,0,null,null,0,null,null,100,null,50,null,null,null,null,null]},"60b4afc97e53d10d439f7f55":{"n":1,"occ":[null,0,null,null,null,null,0,null,null,null,0,null,null,0,null,null,0,null,0,null,null,null,null,null]},"66951f46016a0f001c74d4d9":{"n":2,"occ":[null,50,null,null,null,null,50,null,null,null,50,null,null,50,null,null,50,null,50,null,null,null,null,null]},"670cbca615cc25001cf3b42c":{"n":1,"occ":[null,100,null,null,null,null,100,null,null,null,100,null,null,100,null,null,100,null,100,null,null,null,null,null]},"NLLOC018330":{"n":2,"occ":[null,0,null,null,null,null,0,null,null,null,0,null,null,0,null,null,0,null,0,null,null,null,null,null]},"623cd23341aaac7803818a74":{"n":1,"occ":[null,100,null,null,null,null,100,null,null,null,100,null,null,100,null,null,100,null,100,null,null,null,null,null]},"NLLOC000654":{"n":2,"occ":[null,0,null,null,null,null,0,null,null,null,50,null,null,0,null,null,100,null,100,null,null,null,null,null]},"63457f8ed946662007919dc5":{"n":1,"occ":[null,0,null,null,null,null,0,null,null,null,0,null,null,0,null,null,0,null,0,null,null,null,null,null]},"b6cb6808d82b2b98f2dd06424b91ebe3":{"n":2,"occ":[null,0,null,null,null,null,0,null,null,null,0,null,null,100,null,null,50,null,50,null,null,null,null,null]},"84932176bc569a321e5e7a1fa39c2a9b":{"n":2,"occ":[null,50,null,null,null,null,50,null,null,null,50,null,null,0,null,null,50,null,50,null,null,null,null,null]},"f534e38ceef6e8e4cddf041a06fc42a5":{"n":2,"occ":[null,50,null,null,null,null,50,null,null,null,0,null,null,0,null,null,0,null,0,null,null,null,null,null]},"NLLOC000702":{"n":2,"occ":[null,50,null,null,null,null,50,null,null,null,50,null,null,100,null,null,0,null,0,null,null,null,null,null]},"ebd21c4c8c038fc11e5fc247ec0165ce":{"n":2,"occ":[null,50,null,null,null,null,50,null,null,null,100,null,null,50,null,null,0,null,50,null,null,null,null,null]},"66a103c2eff793001cd63ba4":{"n":2,"occ":[null,0,null,null,null,null,0,null,null,null,0,null,null,0,null,null,0,null,100,null,null,null,null,null]},"NLLOC003997":{"n":2,"occ":[null,50,null,null,null,null,0,null,null,null,0,null,null,0,null,null,0,null,0,null,null,null,null,null]},"836c477400ccab983bed61ced2809716":{"n":2,"occ":[null,0,null,null,null,null,0,null,null,null,0,null,null,0,null,null,50,null,0,null,null,null,null,null]},"ee7a6b2ec7d6c14520c29c1636a789e6":{"n":2,"occ":[null,0,null,null,null,null,0,null,null,null,0,null,null,0,null,null,50,null,50,null,null,null,null,null]},"5ff348df-7755-45f8-830c-c6bef0880b61":{"n":8,"occ":[null,0,null,null,null,null,0,null,null,null,0,null,null,38,null,null,13,null,13,null,null,null,null,null]},"a090dba8-bbe0-4ec7-93e0-c6b7c4c08975":{"n":2,"occ":[null,0,null,null,null,null,0,null,null,null,0,null,null,0,null,null,50,null,50,null,null,null,null,null]},"0127dab3-714d-4a55-b63d-ae865075e79d":{"n":2,"occ":[null,50,null,null,null,null,50,null,null,null,50,null,null,50,null,null,0,null,0,null,null,null,null,null]},"67a31421cbc9ad0f8f225e57":{"n":2,"occ":[null,0,null,null,null,null,0,null,null,null,0,null,null,0,null,null,0,null,0,null,null,null,null,null]},"dc10cb5f-68c5-4c9c-a743-e6698935966c":{"n":2,"occ":[null,50,null,null,null,null,50,null,null,null,50,null,null,0,null,null,0,null,0,null,null,null,null,null]},"f12ba2b4198657fb353a070228db0bad":{"n":2,"occ":[null,50,null,null,null,null,50,null,null,null,50,null,null,50,null,null,100,null,100,null,null,null,null,null]},"60b0e5be26e691328a025e10":{"n":4,"occ":[null,0,null,null,null,null,0,null,null,null,0,null,null,0,null,null,0,null,0,null,null,null,null,null]},"63458074d94666218091c38b":{"n":1,"occ":[null,0,null,null,null,null,0,null,null,null,0,null,null,0,null,null,0,null,0,null,null,null,null,null]},"f090baee-9ea7-425a-970f-9d421a6314ef":{"n":2,"occ":[null,50,null,null,null,null,50,null,null,null,50,null,null,0,null,null,0,null,0,null,null,null,null,null]},"8989cb78a36a12faad09acbc7fe0366a":{"n":2,"occ":[null,0,null,null,null,null,0,null,null,null,0,null,null,0,null,null,0,null,50,null,null,null,null,null]},"b55c5243ecad71e3af3c5f8cbc6945d4":{"n":2,"occ":[null,0,null,null,null,null,0,null,null,null,0,null,null,0,null,null,0,null,0,null,null,null,null,null]},"b792cbc0-8bc0-42d2-818e-8ea5263634b3":{"n":2,"occ":[null,100,null,null,null,null,100,null,null,null,50,null,null,100,null,null,50,null,0,null,null,null,null,null]},"81e25e1c5f0ff2419c35ce81bd2ccd40":{"n":2,"occ":[null,50,null,null,null,null,50,null,null,null,0,null,null,50,null,null,0,null,50,null,null,null,null,null]},"182eb59aad98881cd7ca6ebb5a8b4458":{"n":2,"occ":[null,0,null,null,null,null,0,null,null,null,0,null,null,0,null,null,0,null,0,null,null,null,null,null]},"7fbda26427e028c4d4d1209b06a45acd":{"n":2,"occ":[null,100,null,null,null,null,100,null,null,null,50,null,null,100,null,null,50,null,50,null,null,null,null,null]},"50c3ccd2-26fa-4282-82f7-ec779ff23b19":{"n":2,"occ":[null,0,null,null,null,null,0,null,null,null,0,null,null,0,null,null,0,null,0,null,null,null,null,null]},"9d94c6c0942d7a3640d1624f6acec5b9":{"n":2,"occ":[null,0,null,null,null,null,0,null,null,null,0,null,null,0,null,null,0,null,0,null,null,null,null,null]}}}